{
    "COMMON_MISTAKES": {
        "сметат":"сметаат",
        "превзема":"презема",
        "оддржу":"одржу",
        "ефтин":"евтин",
        "двеста":"двесте",
        "петата":"петтата",
        "пеесет":"педесет",
        "девеесет":"деведесет",
        "тристотини":"триста",
        "допринос":"придонес",
        "вопредвид":"предвид",
        "свати":"сфати",
        "неможе":"не може",
        "коешто":"кое што",
        "којшто":"кој што",
        "којaшто":"којa што",
        "чиешто":"чие што",
        "чијшто":"чиј што",
        "чијашто":"чија што",
        "нај голем":"најголем",
        "по голем":"поголем",
        "туку што":"тукушто",
        "штотуку":"што туку",
        "сé":"сè",
        "сеуште":"сè уште",
        "седодека":"сè додека",
        "Европска комисија":"Европска Комисија",
        "заменик претседател":"заменик-претседател",
        "нетоизнос":"нето-износ",
        "жиросметка":"жиро-сметка",
        "дваесетдневен":"дваесетдневен",
        "одсега":"отсега",
        "одтука":"оттука",
        "подстраница":"потстраница",
        "подкатегорија":"поткатегорија",
        "досега":"досега",
        "одвременавреме":"одвреме-навреме",
        "несакајќи":"несакајќи",
        "филозофија":"философија",
        "филозоф":"философ",
        "зборев":"зборував",
        "збориме":"зборуваме",
        "љуѓе":"луѓе",
        "можи":"може",
        "Фиумичино":"Фјумичино",
        "Њу Јорк":"Њујорк",
        "Ѓенова":"Џенова",
        "Лос Анѓелес":"Лос Анџелес",
        "ХонгКонг":"Хонгконг",
        "Гарсиа":"Гарсија",
        "Википедиа":"Википедија",
        "Гвадалупе":"Гваделуп",
        "Кореа":"Кореја",
        "делимично":"делумно",
        "жмигавци":"трепкачи",
        "запосли":"вработи",
        "заоштри":"заостри",
        "најкасно":"најдоцна",
        "такада":"такашто",
        "увек":"секогаш",
        "чаробни":"волшебни",
        "миља":"милја",
        "миљи":"милји",
        "Пие":"Пиј",
        "Јулие":"Јулиј",
        "Конфучие":"Конфучиј",
        "датабаза":"базанаподатоци",
        "датабазата":"базатанаподатоци",
        "Референци":"Наводи",
        "референци":"наводи",
        "Референции":"Наводи",
        "референции":"наводи",
        "Линкови":"Врски",
        "линкови":"врски",
        "фајлови":"податотеки",
        "екстензија":"наставка",
        "екстензијата":"наставката",
        "екстензиии":"наставки",
        "екстензииите":"наставките",
        "имејлови":"е-пораки",
        "имејли":"е-пораки",
        "краткаприказна":"расказ",
        "краткиприказни":"раскази",
        "мејлови":"е-пораки",
        "мапа":"карта",
        "мапата":"картата",
        "мапи":"карти",
        "мапите":"картите",
        "менаџира":"управува",
        "виџет":"елемент",
        "виџети":"елементи",
        "виџетот":"елементот",
        "виџетите":"елементите",
        "селектира":"одбира",
        "селектиран":"одбран",
        "селектирана":"одбрана",
        "селектирано":"одбрано",
        "сервис":"служба",
        "сервиси":"служби",
        "сервер":"опслужувач",
        "серверот":"опслужувачот",
        "сервери":"опслужувачи",
        "серверите":"опслужувачите",
        "таг":"ознака",
        "тагот":"ознаката",
        "тагови":"ознаки",
        "таговите":"ознаките",
        "интерфејс":"посредник",
        "интерфејсот":"посредникот",
        "хост":"домаќин",
        "Петерсбург":"Петербург",
        "едукација":"образование",
        "Едукација":"Образование",
        "едукацијата":"образованието",
        "едукативен":"образовен",
        "едукативна":"образовна",
        "едукативно":"образовно",
        "едуциран":"образован",
        "едуцирана":"образована",
        "интернационален":"меѓународен",
        "интернационалниот":"меѓународниот",
        "интернационална":"меѓународна",
        "интернационалната":"меѓународната",
        "интернационално":"меѓународно",
        "интернационалното":"меѓународното",
        "интернационални":"меѓународни",
        "интернационалните":"меѓународните",
        "Листи":"Списоци",
        "листи":"списоци",
        "јалистата":"госписокот",
        "креатор":"создавач",
        "креира":"создава",
        "креирај":"создај",
        "креирајте":"создајте",
        "креиран":"создаден",
        "креираниот":"создадениот",
        "креирана":"создадена",
        "креираната":"создадената",
        "креирано":"создадено",
        "креираното":"создаденото",
        "креираните":"создадените",
        "колаборација":"соработка",
        "конектира":"поврзува",
        "конектирај":"поврзи",
        "конектирајте":"поврзете",
        "конектиран":"поврзан",
        "конектираниот":"поврзаниот",
        "конектирана":"поврзана",
        "конектираната":"поврзаната",
        "конектирано":"поврзано",
        "конектираното":"поврзаното",
        "конектираните":"поврзаните",
        "маркиран":"обележан",
        "маркирање":"обележување",
        "Спецификации":"Карактеристики",
        "Листа":"Список",
        "листа":"список",
        "башка":"одделно",
        "комшија":"сосед",
        "комшика":"сосетка",
        "комшивка":"сосетка",
        "пенџер":"прозорец",
        "пенџере":"прозорец"
    },
    "ABBREVIATIONS": {
        "бр.": "број",
        "гр.": "град",
        "др.": "другар",
        "и др.": "и друго",
        "и сл.": "и слично",
        "кн.": "книга",
        "мн.": "множина",
        "на пр.": "на пример",
        "од н.е.": "од нашата ера",
        "пр. н.е.": "пред нашата ера",
        "по Хр.": "по Христа",
        "пр. Хр.": "пред Христа",
        "св.": "свети",
        "сп.": "спореди",
        "ср. р.": "среден род",
        "стр.": "страница",
        "с.": "страница",
        "ст. ст.": "стар стил",
        "чл.": "член",
        "итн.": "и така натаму",
        "арх.": "архитект",
        "бел.": "белешка",
        "забел.": "забелешка",
        "гимн.": "гимназија",
        "ден.": "денар",
        "ген.": "генитив",
        "год.": "година",
        "г.": "година",
        "дем.": "деминутив",
        "едн.": "еднина",
        "ул.": "улица",
        "инж.": "инженер",
        "проф.": "професор",
        "комп.": "компаратив",
        "синг.": "сингулар",
        "студ.": "студент",
        "ак.": "акузатив",
        "бот.": "ботаника",
        "вок.": "вокатив",
        "грам.": "граматика",
        "дат.": "датив",
        "им.": "именка",
        "мат.": "математика",
        "ном.": "номинатив",
        "прил.": "прилог",
        "прид.": "придавка",
        "сврз.": "сврзник",
        "физ.": "физика",
        "хем.": "хемија",
        "пр.н.": "природни науки",
        "аугм.": "аугментатив",
        "геогр.": "географија",
        "истор.": "историја",
        "литер.": "литература",
        "мит.": "митологија",
        "неменл.": "неменливо",
        "поет.": "поетски",
        "зоол.": "зоологија",
        "стсл.": "старословенски",
        "пф.": "перфективен",
        "импф.": "имперфективен",
        "д-р": "доктор",
        "м-р": "магистер",
        "г-ѓа": "госпоѓа",
        "г-ца": "госпоѓица",
        "г-дин": "господин",
        "АСНОМ": "Антифашистичко собрание на народното ослободување на Македонија",
        "НОБ": "Народноослободителна борба",
        "ВМРО": "Внатрешна македонска револуционерна организација",
        "РМ": "Република Македонија",
        "САД": "Соединети Американски Држави",
        "ЗНД": "Заедница на независни држави",
        "СРГ": "Сојузна Република Германија",
        "СРЈ": "Сојузна Република Југославија",
        "ОН": "Обединети нации",
        "ООН": "Организација на обединетите нации",
        "АРМ": "Армија на Република Македонија",
        "МАНУ": "Македонска академија на науки и уметности",
        "МНТ": "Македонски народен театар",
        "ДПМ": "Друштво на писателите на Македонија",
        "МЖ": "Македонски железници",
        "МТВ": "Македонска телевизија",
        "РТВ": "радио-телевизија",
        "ПТТ": "пошта, телеграф, телефон",
        "ЈП": "јавно претпријатие",
        "ЗИК": "земјоделско-индустриски комбинат",
        "ИК": "извршен комитет",
        "ЦО": "централен одбор"
    },
    "WHITELISTED_CHARACTERS": {
        "а": true,
        "б": true,
        "в": true,
        "г": true,
        "д": true,
        "ѓ": true,
        "е": true,
        "ѐ": true,
        "ж": true,
        "з": true,
        "ѕ": true,
        "и": true,
        "ѝ": true,
        "ј": true,
        "к": true,
        "л": true,
        "љ": true,
        "м": true,
        "н": true,
        "њ": true,
        "о": true,
        "п": true,
        "р": true,
        "с": true,
        "т": true,
        "ќ": true,
        "у": true,
        "ф": true,
        "х": true,
        "ц": true,
        "ч": true,
        "џ": true,
        "ш": true,
        "А": true,
        "Б": true,
        "В": true,
        "Г": true,
        "Д": true,
        "Ѓ": true,
        "Е": true,
        "Ѐ": true,
        "Ж": true,
        "З": true,
        "Ѕ": true,
        "И": true,
        "Ѝ": true,
        "Ј": true,
        "К": true,
        "Л": true,
        "Љ": true,
        "М": true,
        "Н": true,
        "Њ": true,
        "О": true,
        "П": true,
        "Р": true,
        "С": true,
        "Т": true,
        "Ќ": true,
        "У": true,
        "Ф": true,
        "Х": true,
        "Ц": true,
        "Ч": true,
        "Џ": true,
        "Ш": true,
        ";": true,
        "„": true,
        "“": true,
        ".": true,
        "?": true,
        "!": true,
        "(": true,
        ")": true,
        ",": true,
        "—": true,
        "-": true,
        ":": true,
        " ": true
    }
}
